modelpricing_ai/__init__.py
modelpricing_ai/async_client.py
modelpricing_ai/client.py
modelpricing_ai/errors.py
modelpricing_ai/models.py
modelpricing_ai/test_async_client.py
modelpricing_ai/test_client.py
modelpricing_ai-0.0.1a1.dist-info/METADATA
modelpricing_ai-0.0.1a1.dist-info/WHEEL
modelpricing_ai-0.0.1a1.dist-info/licenses/LICENSE
modelpricing_ai-0.0.1a1.dist-info/RECORD
