Metadata-Version: 2.4
Name: modelpricing-ai
Version: 0.0.1a1
Summary: Python client for ModelPricing.ai cost estimates
Project-URL: Homepage, https://modelpricing.ai
Author: ModelPricing.ai
License: MIT
License-File: LICENSE
Classifier: Intended Audience :: Developers
Classifier: License :: OSI Approved :: MIT License
Classifier: Programming Language :: Python :: 3
Classifier: Programming Language :: Python :: 3 :: Only
Classifier: Programming Language :: Python :: 3.8
Classifier: Programming Language :: Python :: 3.9
Classifier: Programming Language :: Python :: 3.10
Classifier: Programming Language :: Python :: 3.11
Classifier: Programming Language :: Python :: 3.12
Classifier: Programming Language :: Python :: 3.13
Classifier: Topic :: Software Development :: Libraries :: Python Modules
Requires-Python: >=3.8
Requires-Dist: aiohttp>=3.9.0
Requires-Dist: pydantic>=2.3.0
Requires-Dist: requests>=2.31.0
Requires-Dist: tenacity>=8.0.0
Provides-Extra: dev
Requires-Dist: build>=1.2.1; extra == 'dev'
Requires-Dist: pytest-asyncio>=0.23; extra == 'dev'
Requires-Dist: pytest>=7.0; extra == 'dev'
Requires-Dist: twine>=5.0.0; extra == 'dev'
